odoo/addons/shopfloor_delivery_shipment_mobile/README.rst
odoo/addons/shopfloor_delivery_shipment_mobile/__init__.py
odoo/addons/shopfloor_delivery_shipment_mobile/__manifest__.py
odoo/addons/shopfloor_delivery_shipment_mobile/i18n/es_AR.po
odoo/addons/shopfloor_delivery_shipment_mobile/i18n/it.po
odoo/addons/shopfloor_delivery_shipment_mobile/i18n/pt_BR.po
odoo/addons/shopfloor_delivery_shipment_mobile/i18n/shopfloor_delivery_shipment_mobile.pot
odoo/addons/shopfloor_delivery_shipment_mobile/readme/CONTRIBUTORS.md
odoo/addons/shopfloor_delivery_shipment_mobile/readme/DESCRIPTION.md
odoo/addons/shopfloor_delivery_shipment_mobile/static/description/icon.png
odoo/addons/shopfloor_delivery_shipment_mobile/static/description/index.html
odoo/addons/shopfloor_delivery_shipment_mobile/static/src/demo/demo.delivery_shipment.esm.js
odoo/addons/shopfloor_delivery_shipment_mobile/static/src/scenario/delivery_shipment.esm.js
odoo/addons/shopfloor_delivery_shipment_mobile/templates/assets.xml
odoo_addon_shopfloor_delivery_shipment_mobile-18.0.1.0.0.3.dist-info/METADATA
odoo_addon_shopfloor_delivery_shipment_mobile-18.0.1.0.0.3.dist-info/WHEEL
odoo_addon_shopfloor_delivery_shipment_mobile-18.0.1.0.0.3.dist-info/top_level.txt
odoo_addon_shopfloor_delivery_shipment_mobile-18.0.1.0.0.3.dist-info/RECORD
